[
  {
    "id": "20260415131237348276-rua-38790-sent",
    "ts": "2026-04-15T13:12:37",
    "date": "2026-04-15",
    "time": "13:12:37",
    "market": "rua",
    "market_name": "Rua (4m 40s)",
    "market_id": "38790",
    "status": "sent",
    "rec": "MAIS",
    "kind": "AO VIVO",
    "amount": 4.0,
    "currency": "BRLX",
    "odd": "0.80 (1.25x)",
    "conf_pct": 97,
    "detail": "Ordem automatica enviada: AO VIVO MAIS | 4.00 BRLX | odd 0.80 (1.25x) | lucro esp. 1.00 BRLX | 97% | topo real do book 0.99 (1.01x) | alvo aleatorio 1.25x",
    "api_status": 201,
    "execution": "topo real do book 0.99 (1.01x) | alvo aleatorio 1.25x",
    "accepted_by_api": true,
    "confirmed_position": true,
    "outcome": "win",
    "resolved_at": "2026-04-15 13:14:23"
  },
  {
    "id": "20260415131639409560-rua-38792-sent",
    "ts": "2026-04-15T13:16:39",
    "date": "2026-04-15",
    "time": "13:16:39",
    "market": "rua",
    "market_name": "Rua (4m 40s)",
    "market_id": "38792",
    "status": "sent",
    "rec": "MAIS",
    "kind": "AO VIVO",
    "amount": 10.0,
    "currency": "BRLX",
    "odd": "0.78 (1.28x)",
    "conf_pct": 97,
    "detail": "Ordem automatica enviada: AO VIVO MAIS | 10.00 BRLX | odd 0.78 (1.28x) | lucro esp. 2.82 BRLX | 97% | topo real do book 0.95 (1.05x) | alvo aleatorio 1.28x",
    "api_status": 201,
    "execution": "topo real do book 0.95 (1.05x) | alvo aleatorio 1.28x",
    "accepted_by_api": true,
    "confirmed_position": true,
    "outcome": null,
    "resolved_at": null
  },
  {
    "id": "20260415131751441725-rodovia-38791-error",
    "ts": "2026-04-15T13:17:51",
    "date": "2026-04-15",
    "time": "13:17:51",
    "market": "rodovia",
    "market_name": "Rodovia (5 min)",
    "market_id": "38791",
    "status": "error",
    "rec": "MAIS",
    "kind": "AO VIVO",
    "amount": 10.0,
    "currency": "BRLX",
    "odd": "0.86 (1.16x)",
    "conf_pct": 96,
    "detail": "Previsões encerradas para este mercado.",
    "api_status": 400,
    "execution": "topo real do book 0.86 (1.16x) | alvo aleatorio 1.32x",
    "accepted_by_api": false,
    "confirmed_position": false,
    "outcome": null,
    "resolved_at": null
  },
  {
    "id": "20260415131823996351-rua-38792-sent",
    "ts": "2026-04-15T13:18:23",
    "date": "2026-04-15",
    "time": "13:18:23",
    "market": "rua",
    "market_name": "Rua (4m 40s)",
    "market_id": "38792",
    "status": "sent",
    "rec": "MAIS",
    "kind": "AO VIVO",
    "amount": 10.0,
    "currency": "BRLX",
    "odd": "0.70 (1.43x)",
    "conf_pct": 97,
    "detail": "Ordem automatica enviada: AO VIVO MAIS | 10.00 BRLX | odd 0.70 (1.43x) | lucro esp. 4.29 BRLX | 97% | topo real do book 0.65 (1.55x) | alvo aleatorio 1.43x",
    "api_status": 201,
    "execution": "topo real do book 0.65 (1.55x) | alvo aleatorio 1.43x",
    "accepted_by_api": true,
    "confirmed_position": true,
    "outcome": "win",
    "resolved_at": "2026-04-15 13:18:26"
  },
  {
    "id": "20260415132427403056-rodovia-38798-sent",
    "ts": "2026-04-15T13:24:27",
    "date": "2026-04-15",
    "time": "13:24:27",
    "market": "rodovia",
    "market_name": "Rodovia (5 min)",
    "market_id": "38798",
    "status": "sent",
    "rec": "MAIS",
    "kind": "AO VIVO",
    "amount": 10.0,
    "currency": "BRLX",
    "odd": "0.75 (1.33x)",
    "conf_pct": 86,
    "detail": "Ordem automatica enviada: AO VIVO MAIS | 10.00 BRLX | odd 0.75 (1.33x) | lucro esp. 3.33 BRLX | 86% | topo real do book 0.86 (1.16x) | alvo aleatorio 1.34x",
    "api_status": 201,
    "execution": "topo real do book 0.86 (1.16x) | alvo aleatorio 1.34x",
    "accepted_by_api": true,
    "confirmed_position": true,
    "outcome": "win",
    "resolved_at": "2026-04-15 13:27:34"
  },
  {
    "id": "20260415132726809028-rua-38799-error",
    "ts": "2026-04-15T13:27:26",
    "date": "2026-04-15",
    "time": "13:27:26",
    "market": "rua",
    "market_name": "Rua (4m 40s)",
    "market_id": "38799",
    "status": "error",
    "rec": "MAIS",
    "kind": "AO VIVO",
    "amount": 10.0,
    "currency": "BRLX",
    "odd": "0.65 (1.55x)",
    "conf_pct": 96,
    "detail": "Mercado indisponível no momento.",
    "api_status": 400,
    "execution": "topo real do book 0.65 (1.55x) | alvo aleatorio 1.33x",
    "accepted_by_api": false,
    "confirmed_position": false,
    "outcome": null,
    "resolved_at": null
  },
  {
    "id": "20260415132733075813-rodovia-38798-error",
    "ts": "2026-04-15T13:27:33",
    "date": "2026-04-15",
    "time": "13:27:33",
    "market": "rodovia",
    "market_name": "Rodovia (5 min)",
    "market_id": "38798",
    "status": "error",
    "rec": "MAIS",
    "kind": "AO VIVO",
    "amount": 10.0,
    "currency": "BRLX",
    "odd": "0.86 (1.16x)",
    "conf_pct": 96,
    "detail": "Previsões encerradas para este mercado.",
    "api_status": 400,
    "execution": "topo real do book 0.86 (1.16x) | alvo aleatorio 1.54x",
    "accepted_by_api": false,
    "confirmed_position": false,
    "outcome": null,
    "resolved_at": null
  },
  {
    "id": "20260415132902785498-rodovia-38802-sent",
    "ts": "2026-04-15T13:29:02",
    "date": "2026-04-15",
    "time": "13:29:02",
    "market": "rodovia",
    "market_name": "Rodovia (5 min)",
    "market_id": "38802",
    "status": "sent",
    "rec": "MAIS",
    "kind": "AO VIVO",
    "amount": 10.0,
    "currency": "BRLX",
    "odd": "0.68 (1.47x)",
    "conf_pct": 92,
    "detail": "Ordem automatica enviada: AO VIVO MAIS | 10.00 BRLX | odd 0.68 (1.47x) | lucro esp. 4.71 BRLX | 92% | topo real do book 0.65 (1.55x) | alvo aleatorio 1.48x",
    "api_status": 201,
    "execution": "topo real do book 0.65 (1.55x) | alvo aleatorio 1.48x",
    "accepted_by_api": true,
    "confirmed_position": true,
    "outcome": "win",
    "resolved_at": "2026-04-15 13:31:55"
  },
  {
    "id": "20260415133439107739-rua-38805-sent",
    "ts": "2026-04-15T13:34:39",
    "date": "2026-04-15",
    "time": "13:34:39",
    "market": "rua",
    "market_name": "Rua (4m 40s)",
    "market_id": "38805",
    "status": "sent",
    "rec": "MAIS",
    "kind": "AO VIVO",
    "amount": 10.0,
    "currency": "BRLX",
    "odd": "0.72 (1.39x)",
    "conf_pct": 84,
    "detail": "Ordem automatica enviada: AO VIVO MAIS | 10.00 BRLX | odd 0.72 (1.39x) | lucro esp. 3.89 BRLX | 84% | topo real do book 0.99 (1.01x) | alvo aleatorio 1.38x",
    "api_status": 201,
    "execution": "topo real do book 0.99 (1.01x) | alvo aleatorio 1.38x",
    "accepted_by_api": true,
    "confirmed_position": true,
    "outcome": null,
    "resolved_at": null
  },
  {
    "id": "20260415202016238535-rodovia-39075-sent",
    "ts": "2026-04-15T20:20:16",
    "date": "2026-04-15",
    "time": "20:20:16",
    "market": "rodovia",
    "market_name": "Rodovia (5 min)",
    "market_id": "39075",
    "status": "sent",
    "rec": "MAIS",
    "kind": "TESTE",
    "amount": 1.01,
    "currency": "BRLX",
    "odd": "0.68 (1.47x)",
    "conf_pct": null,
    "detail": "Ordem automatica enviada: TESTE MAIS | 1.01 BRLX | odd 0.68 (1.47x) | lucro esp. 0.48 BRLX | topo real do book 0.95 (1.05x) | alvo aleatorio 1.48x",
    "api_status": 201,
    "execution": "topo real do book 0.95 (1.05x) | alvo aleatorio 1.48x",
    "accepted_by_api": true,
    "confirmed_position": true,
    "outcome": "loss",
    "resolved_at": "2026-04-15 20:24:15"
  },
  {
    "id": "20260415202111056278-rua-39074-error",
    "ts": "2026-04-15T20:21:11",
    "date": "2026-04-15",
    "time": "20:21:11",
    "market": "rua",
    "market_name": "Rua (4m 40s)",
    "market_id": "39074",
    "status": "error",
    "rec": "MAIS",
    "kind": "AO VIVO",
    "amount": 29.77,
    "currency": "BRLX",
    "odd": "0.65 (1.55x)",
    "conf_pct": 96,
    "detail": "Mercado indisponível no momento.",
    "api_status": 400,
    "execution": "topo real do book 0.65 (1.55x) | alvo aleatorio 1.40x",
    "accepted_by_api": false,
    "confirmed_position": false,
    "outcome": null,
    "resolved_at": null
  },
  {
    "id": "20260415202322695246-rua-39077-sent",
    "ts": "2026-04-15T20:23:22",
    "date": "2026-04-15",
    "time": "20:23:22",
    "market": "rua",
    "market_name": "Rua (4m 40s)",
    "market_id": "39077",
    "status": "sent",
    "rec": "MAIS",
    "kind": "AO VIVO",
    "amount": 29.77,
    "currency": "BRLX",
    "odd": "0.66 (1.52x)",
    "conf_pct": 92,
    "detail": "Ordem automatica enviada: AO VIVO MAIS | 29.77 BRLX | odd 0.66 (1.52x) | lucro esp. 15.34 BRLX | 92% | topo real do book 0.79 (1.27x) | alvo aleatorio 1.52x",
    "api_status": 201,
    "execution": "topo real do book 0.79 (1.27x) | alvo aleatorio 1.52x",
    "accepted_by_api": true,
    "confirmed_position": true,
    "outcome": "loss",
    "resolved_at": "2026-04-15 20:25:44"
  },
  {
    "id": "20260415202550419759-rodovia-39078-sent",
    "ts": "2026-04-15T20:25:50",
    "date": "2026-04-15",
    "time": "20:25:50",
    "market": "rodovia",
    "market_name": "Rodovia (5 min)",
    "market_id": "39078",
    "status": "sent",
    "rec": "ATE",
    "kind": "AO VIVO",
    "amount": 26.68,
    "currency": "BRLX",
    "odd": "0.69 (1.45x)",
    "conf_pct": 86,
    "detail": "Ordem automatica enviada: AO VIVO ATE | 26.68 BRLX | odd 0.69 (1.45x) | lucro esp. 11.99 BRLX | 86% | topo real do book 0.95 (1.05x) | alvo aleatorio 1.45x",
    "api_status": 201,
    "execution": "topo real do book 0.95 (1.05x) | alvo aleatorio 1.45x",
    "accepted_by_api": true,
    "confirmed_position": true,
    "outcome": "win",
    "resolved_at": "2026-04-15 20:29:16"
  },
  {
    "id": "20260415203019753966-rua-39080-error",
    "ts": "2026-04-15T20:30:19",
    "date": "2026-04-15",
    "time": "20:30:19",
    "market": "rua",
    "market_name": "Rua (4m 40s)",
    "market_id": "39080",
    "status": "error",
    "rec": "MAIS",
    "kind": "AO VIVO",
    "amount": 24.01,
    "currency": "BRLX",
    "odd": "0.65 (1.55x)",
    "conf_pct": 96,
    "detail": "Mercado indisponível no momento.",
    "api_status": 400,
    "execution": "topo real do book 0.65 (1.55x) | alvo aleatorio 1.53x",
    "accepted_by_api": false,
    "confirmed_position": false,
    "outcome": null,
    "resolved_at": null
  },
  {
    "id": "20260415203056453088-rodovia-39081-sent",
    "ts": "2026-04-15T20:30:56",
    "date": "2026-04-15",
    "time": "20:30:56",
    "market": "rodovia",
    "market_name": "Rodovia (5 min)",
    "market_id": "39081",
    "status": "sent",
    "rec": "MAIS",
    "kind": "AO VIVO",
    "amount": 27.62,
    "currency": "BRLX",
    "odd": "0.79 (1.27x)",
    "conf_pct": 91,
    "detail": "Ordem automatica enviada: AO VIVO MAIS | 27.62 BRLX | odd 0.79 (1.27x) | lucro esp. 7.34 BRLX | 91% | topo real do book 0.65 (1.55x) | alvo aleatorio 1.26x",
    "api_status": 201,
    "execution": "topo real do book 0.65 (1.55x) | alvo aleatorio 1.26x",
    "accepted_by_api": true,
    "confirmed_position": true,
    "outcome": "loss",
    "resolved_at": "2026-04-15 20:34:14"
  },
  {
    "id": "20260415204150791346-rua-39088-sent",
    "ts": "2026-04-15T20:41:50",
    "date": "2026-04-15",
    "time": "20:41:50",
    "market": "rua",
    "market_name": "Rua (4m 40s)",
    "market_id": "39088",
    "status": "sent",
    "rec": "MAIS",
    "kind": "AO VIVO",
    "amount": 24.87,
    "currency": "BRLX",
    "odd": "0.69 (1.45x)",
    "conf_pct": 90,
    "detail": "Ordem automatica enviada: AO VIVO MAIS | 24.87 BRLX | odd 0.69 (1.45x) | lucro esp. 11.17 BRLX | 90% | topo real do book 0.65 (1.55x) | alvo aleatorio 1.45x",
    "api_status": 201,
    "execution": "topo real do book 0.65 (1.55x) | alvo aleatorio 1.45x",
    "accepted_by_api": true,
    "confirmed_position": true,
    "outcome": "win",
    "resolved_at": "2026-04-15 20:44:01"
  },
  {
    "id": "20260415204338271960-rodovia-39087-error",
    "ts": "2026-04-15T20:43:38",
    "date": "2026-04-15",
    "time": "20:43:38",
    "market": "rodovia",
    "market_name": "Rodovia (5 min)",
    "market_id": "39087",
    "status": "error",
    "rec": "MAIS",
    "kind": "AO VIVO",
    "amount": 24.87,
    "currency": "BRLX",
    "odd": "0.65 (1.55x)",
    "conf_pct": 96,
    "detail": "Mercado indisponível no momento.",
    "api_status": 400,
    "execution": "topo real do book 0.65 (1.55x) | alvo aleatorio 1.36x",
    "accepted_by_api": false,
    "confirmed_position": false,
    "outcome": null,
    "resolved_at": null
  },
  {
    "id": "20260415204827451320-rodovia-39090-error",
    "ts": "2026-04-15T20:48:27",
    "date": "2026-04-15",
    "time": "20:48:27",
    "market": "rodovia",
    "market_name": "Rodovia (5 min)",
    "market_id": "39090",
    "status": "error",
    "rec": "MAIS",
    "kind": "AO VIVO",
    "amount": 22.38,
    "currency": "BRLX",
    "odd": "0.65 (1.55x)",
    "conf_pct": 96,
    "detail": "Mercado indisponível no momento.",
    "api_status": 400,
    "execution": "topo real do book 0.65 (1.55x) | alvo aleatorio 1.27x",
    "accepted_by_api": false,
    "confirmed_position": false,
    "outcome": null,
    "resolved_at": null
  },
  {
    "id": "20260415204843485194-rua-39091-error",
    "ts": "2026-04-15T20:48:43",
    "date": "2026-04-15",
    "time": "20:48:43",
    "market": "rua",
    "market_name": "Rua (4m 40s)",
    "market_id": "39091",
    "status": "error",
    "rec": "MAIS",
    "kind": "AO VIVO",
    "amount": 24.87,
    "currency": "BRLX",
    "odd": "0.65 (1.55x)",
    "conf_pct": 96,
    "detail": "Mercado indisponível no momento.",
    "api_status": 400,
    "execution": "topo real do book 0.65 (1.55x) | alvo aleatorio 1.38x",
    "accepted_by_api": false,
    "confirmed_position": false,
    "outcome": null,
    "resolved_at": null
  },
  {
    "id": "20260415204947856338-rodovia-39093-sent",
    "ts": "2026-04-15T20:49:47",
    "date": "2026-04-15",
    "time": "20:49:47",
    "market": "rodovia",
    "market_name": "Rodovia (5 min)",
    "market_id": "39093",
    "status": "sent",
    "rec": "MAIS",
    "kind": "AO VIVO",
    "amount": 24.87,
    "currency": "BRLX",
    "odd": "0.76 (1.32x)",
    "conf_pct": 91,
    "detail": "Ordem automatica enviada: AO VIVO MAIS | 24.87 BRLX | odd 0.76 (1.32x) | lucro esp. 7.85 BRLX | 91% | topo real do book 0.90 (1.11x) | alvo aleatorio 1.32x",
    "api_status": 201,
    "execution": "topo real do book 0.90 (1.11x) | alvo aleatorio 1.32x",
    "accepted_by_api": true,
    "confirmed_position": true,
    "outcome": "loss",
    "resolved_at": "2026-04-15 20:53:29"
  },
  {
    "id": "20260415205535711087-rua-39096-sent",
    "ts": "2026-04-15T20:55:35",
    "date": "2026-04-15",
    "time": "20:55:35",
    "market": "rua",
    "market_name": "Rua (4m 40s)",
    "market_id": "39096",
    "status": "sent",
    "rec": "MAIS",
    "kind": "AO VIVO",
    "amount": 22.37,
    "currency": "BRLX",
    "odd": "0.72 (1.39x)",
    "conf_pct": 95,
    "detail": "Ordem automatica enviada: AO VIVO MAIS | 22.37 BRLX | odd 0.72 (1.39x) | lucro esp. 8.70 BRLX | 95% | topo real do book 0.90 (1.11x) | alvo aleatorio 1.39x",
    "api_status": 201,
    "execution": "topo real do book 0.90 (1.11x) | alvo aleatorio 1.39x",
    "accepted_by_api": true,
    "confirmed_position": true,
    "outcome": null,
    "resolved_at": null
  }
]